airlango_mystic/__init__.py
airlango_mystic/logger.py
airlango_mystic/mystic.py
airlango_mystic/vims_pb2.py
airlango_mystic/vims_pb2_grpc.py
airlango_mystic-0.0.1a0.dist-info/LICENSE
airlango_mystic-0.0.1a0.dist-info/METADATA
airlango_mystic-0.0.1a0.dist-info/WHEEL
airlango_mystic-0.0.1a0.dist-info/top_level.txt
airlango_mystic-0.0.1a0.dist-info/RECORD
